ct_analyser/__init__.py
ct_analyser/cta.py
ct_analyser/mask.py
ct_analyser/segment.py
ct_analyser/Assets/Icon.png
ct_analyser/Data/Patients/Chest_CT/1-01.dcm
ct_analyser/Data/Patients/Chest_CT/1-02.dcm
ct_analyser/Data/Patients/Chest_CT/1-03.dcm
ct_analyser/Data/Patients/Chest_CT/1-04.dcm
ct_analyser/Data/Patients/Chest_CT/1-05.dcm
ct_analyser/Data/Patients/Chest_CT/1-06.dcm
ct_analyser/Data/Patients/Chest_CT/1-07.dcm
ct_analyser/Data/Patients/Chest_CT/1-08.dcm
ct_analyser/Data/Patients/Chest_CT/1-09.dcm
ct_analyser/Data/Patients/Chest_CT/1-10.dcm
ct_analyser/Data/Patients/Chest_CT/1-11.dcm
ct_analyser/Data/Patients/Chest_CT/1-12.dcm
ct_analyser/Data/Patients/Chest_CT/1-13.dcm
ct_analyser/Data/Patients/Chest_CT/1-14.dcm
ct_analyser/Data/Patients/Chest_CT/1-15.dcm
ct_analyser/Data/Patients/Chest_CT/1-16.dcm
ct_analyser/Data/Patients/Chest_CT/1-17.dcm
ct_analyser/Data/Patients/Chest_CT/1-18.dcm
ct_analyser/Data/Patients/Chest_CT/1-19.dcm
ct_analyser/Data/Patients/Chest_CT/1-20.dcm
ct_analyser/Data/Patients/Chest_CT/1-21.dcm
ct_analyser/Data/Patients/Chest_CT/1-22.dcm
ct_analyser/Data/Patients/Chest_CT/1-23.dcm
ct_analyser/Data/Patients/Chest_CT/1-24.dcm
ct_analyser/Data/Patients/Chest_CT/1-25.dcm
ct_analyser/Data/Patients/Chest_CT/1-26.dcm
ct_analyser/Data/Patients/Chest_CT/1-27.dcm
ct_analyser/Data/Patients/Chest_CT/1-28.dcm
ct_analyser/Data/Patients/Chest_CT/1-29.dcm
ct_analyser/Data/Patients/Chest_CT/1-30.dcm
ct_analyser/Data/Patients/Chest_CT/1-31.dcm
ct_analyser/Data/Patients/Chest_CT/1-32.dcm
ct_analyser/Data/Patients/Chest_CT/1-33.dcm
ct_analyser/Data/Patients/Chest_CT/1-34.dcm
ct_analyser/Data/Patients/Chest_CT/1-35.dcm
ct_analyser/Data/Patients/Chest_CT/1-36.dcm
ct_analyser/Data/Patients/Chest_CT/1-37.dcm
ct_analyser/Data/Patients/Chest_CT/1-38.dcm
ct_analyser/Data/Patients/Chest_CT/1-39.dcm
ct_analyser/Data/Patients/Chest_CT/1-40.dcm
ct_analyser/Data/Patients/Chest_CT/1-41.dcm
ct_analyser/Data/Patients/Chest_CT/1-42.dcm
ct_analyser-0.1.2.dist-info/LICENSE
ct_analyser-0.1.2.dist-info/METADATA
ct_analyser-0.1.2.dist-info/WHEEL
ct_analyser-0.1.2.dist-info/top_level.txt
ct_analyser-0.1.2.dist-info/RECORD
