Metadata-Version: 2.1
Name: ct-analyser
Version: 0.1.2
Summary: A Python package for analysing CT scans
Author: Ria Luchun and Thomas Pons
License: The MIT License (MIT)
Classifier: Programming Language :: Python :: 3.8
Classifier: License :: OSI Approved :: MIT License
Classifier: Operating System :: OS Independent
Requires-Python: >=3.8.8
License-File: LICENSE
Requires-Dist: matplotlib (>=3.6.2)
Requires-Dist: numpy (>=1.24.0)
Requires-Dist: scipy (>=1.9.3)
Requires-Dist: pandas (>=1.5.2)
Requires-Dist: scikit-image (>=0.19.3)
Requires-Dist: pydicom (>=2.3.1)
Requires-Dist: pygame (>=2.1.2)
Requires-Dist: python-slugify (>=5.0.2)
Requires-Dist: pytest (>=7.2.0)
